scpclient.py
scpclient-0.7.dist-info/DESCRIPTION.rst
scpclient-0.7.dist-info/METADATA
scpclient-0.7.dist-info/RECORD
scpclient-0.7.dist-info/WHEEL
scpclient-0.7.dist-info/metadata.json
scpclient-0.7.dist-info/top_level.txt
