Metadata-Version: 2.0
Name: scpclient
Version: 0.7
Summary: scp client, for use with paramiko.
Home-page: https://bitbucket.org/ericvsmith/scpclient
Author: Eric V. Smith
Author-email: eric@trueblade.com
License: Apache License Version 2.0
Platform: UNKNOWN
Classifier: Development Status :: 4 - Beta
Classifier: Intended Audience :: Developers
Classifier: License :: OSI Approved :: Apache Software License
Classifier: Topic :: Software Development :: Libraries :: Python Modules
Classifier: Topic :: Security :: Cryptography
Classifier: Programming Language :: Python :: 2.6
Classifier: Programming Language :: Python :: 2.7
